cb_i18n/__init__.py
cb_i18n/translator.py
cb_i18n-1.0.4.dist-info/LICENSE
cb_i18n-1.0.4.dist-info/METADATA
cb_i18n-1.0.4.dist-info/WHEEL
cb_i18n-1.0.4.dist-info/top_level.txt
cb_i18n-1.0.4.dist-info/RECORD
