Metadata-Version: 2.1
Name: cb-i18n
Version: 1.0.4
Summary: Advanced internationalisation (i18n) support for Discord bots, originally developed for ClansBot
Home-page: https://github.com/LiTechO/cb-i18n
Author: weerdy15
License: MIT
Project-URL: Issue tracker, https://github.com/LiTech/cb-i18n/issues
Platform: UNKNOWN
Classifier: Development Status :: 5 - Production/Stable
Classifier: Intended Audience :: Developers
Classifier: Natural Language :: English
Classifier: Programming Language :: Python :: 3.8
Classifier: Programming Language :: Python :: 3.9
Classifier: Programming Language :: Python :: 3.10
Classifier: Topic :: Utilities
Requires-Python: >=3.8.0
License-File: LICENSE
